ci_starter/__init__.py
ci_starter/action.py
ci_starter/assets/toml/semantic-release.toml
ci_starter/assets/workflows/build.yml
ci_starter/assets/workflows/continuous-delivery.yml
ci_starter/assets/workflows/release.yml
ci_starter/assets/workflows/test-e2e.yml
ci_starter/assets/workflows/verify-upstream-has-not-changed.sh
ci_starter/bases.py
ci_starter/cli/__init__.py
ci_starter/cli/callbacks.py
ci_starter/cli/validations.py
ci_starter/constants.py
ci_starter/contracts.py
ci_starter/dataclasses.py
ci_starter/errors.py
ci_starter/git_helpers.py
ci_starter/logging_conf.py
ci_starter/placeholder.py
ci_starter/presets.py
ci_starter/semantic_release_config.py
ci_starter/step.py
ci_starter/utils.py
ci_starter-0.10.6.dist-info/WHEEL
ci_starter-0.10.6.dist-info/entry_points.txt
ci_starter-0.10.6.dist-info/METADATA
ci_starter-0.10.6.dist-info/RECORD
