Metadata-Version: 2.4
Name: ci-starter
Version: 0.10.6
Summary: Kickstarts the semantic release pipeline for your Python project
Keywords: semantic version,semantic release,ci/cd,convetional commits,python-semantic-release
Author: fleetingbytes
Author-email: fleetingbytes <7075397+fleetingbytes@users.noreply.github.com>
License-Expression: BSD-2-Clause
Classifier: Development Status :: 4 - Beta
Classifier: License :: OSI Approved :: BSD License
Classifier: Programming Language :: Python :: 3.11
Classifier: Programming Language :: Unix Shell
Classifier: Topic :: Software Development :: Version Control :: Git
Requires-Dist: click>=8.3
Requires-Dist: gitpython>=3.1.45
Requires-Dist: importlib-resources>=5.10 ; python_full_version < '3.12'
Requires-Dist: platformdirs>=4.4.0
Requires-Dist: requests>=2.32.5
Requires-Dist: ruamel-yaml>=0.18.15
Requires-Dist: semver>=3.0.4
Requires-Dist: tomli-w>=1.2.0
Requires-Python: >=3.11
Project-URL: Changelog, http://github.com/fleetingbytes/ci-starter/blob/master/CHANGELOG.md
Project-URL: Documentation, http://github.com/fleetingbytes/ci-starter/blob/master/README.md
Project-URL: Homepage, http://github.com/fleetingbytes/ci-starter
Project-URL: Issues, http://github.com/fleetingbytes/ci-starter/issues
Project-URL: Repository, http://github.com/fleetingbytes/ci-starter.git
